efficient_llm/ADVANCED.md
efficient_llm/README.md
efficient_llm/__init__.py
efficient_llm/config.py
efficient_llm/download_dots_ocr.py
efficient_llm/engine.py
efficient_llm/pipeline.py
efficient_llm/prompts.py
efficient_llm/requirements.txt
efficient_llm/run_pipeline.py
efficient_llm/utils.py
local_dual_llm/README.md
local_dual_llm/__init__.py
local_dual_llm/config.py
local_dual_llm/engine.py
local_dual_llm/example_test_batch.py
local_dual_llm/pipeline.py
local_dual_llm/prompts.py
local_dual_llm/requirements.txt
local_dual_llm/utils.py
pure_visual_grounder-1.0.8.dist-info/licenses/LICENSE
pure_visual_grounding/README.md
pure_visual_grounding/__init__.py
pure_visual_grounding/core.py
pure_visual_grounding/json_cleaner.py
pure_visual_grounding/prompts.py
pure_visual_grounding/utils.py
pure_visual_grounder-1.0.8.dist-info/METADATA
pure_visual_grounder-1.0.8.dist-info/WHEEL
pure_visual_grounder-1.0.8.dist-info/entry_points.txt
pure_visual_grounder-1.0.8.dist-info/top_level.txt
pure_visual_grounder-1.0.8.dist-info/RECORD
