Metadata-Version: 2.4
Name: pure-visual-grounder
Version: 1.0.8
Summary: A package for processing PDFs with vision-based language models
Author: Strategion
Author-email: Strategion <development@strategion.de>
License: MIT
Classifier: Development Status :: 4 - Beta
Classifier: Intended Audience :: Developers
Classifier: Operating System :: OS Independent
Classifier: Programming Language :: Python :: 3
Classifier: Programming Language :: Python :: 3.8
Classifier: Programming Language :: Python :: 3.9
Classifier: Programming Language :: Python :: 3.10
Classifier: Programming Language :: Python :: 3.11
Requires-Python: >=3.8
License-File: LICENSE
Requires-Dist: langchain~=0.3.27
Requires-Dist: PyMuPDF>=1.26.5
Requires-Dist: langchain-core~=0.3.72
Requires-Dist: pathlib~=1.0.1
Requires-Dist: langsmith>=0.1.17
Provides-Extra: local-dual-llm
Requires-Dist: torch==2.9.1; extra == "local-dual-llm"
Requires-Dist: torchvision==0.24.1; extra == "local-dual-llm"
Requires-Dist: pymupdf==1.26.6; extra == "local-dual-llm"
Requires-Dist: transformers==4.57.3; extra == "local-dual-llm"
Requires-Dist: accelerate==1.12.0; extra == "local-dual-llm"
Requires-Dist: qwen_vl_utils==0.0.14; extra == "local-dual-llm"
Provides-Extra: efficient-llm
Requires-Dist: torch>=2.7.0; extra == "efficient-llm"
Requires-Dist: torchvision>=0.22.0; extra == "efficient-llm"
Requires-Dist: torchaudio>=2.7.0; extra == "efficient-llm"
Requires-Dist: transformers>=4.57.0; extra == "efficient-llm"
Requires-Dist: accelerate>=1.12.0; extra == "efficient-llm"
Requires-Dist: sentencepiece>=0.1.99; extra == "efficient-llm"
Requires-Dist: protobuf>=4.25.0; extra == "efficient-llm"
Requires-Dist: pillow>=10.0.0; extra == "efficient-llm"
Requires-Dist: pymupdf>=1.26.0; extra == "efficient-llm"
Requires-Dist: qwen-vl-utils>=0.0.14; extra == "efficient-llm"
Requires-Dist: numpy>=1.26.0; extra == "efficient-llm"
Requires-Dist: tqdm>=4.66.0; extra == "efficient-llm"
Requires-Dist: psutil>=5.9.0; extra == "efficient-llm"
Requires-Dist: huggingface-hub>=0.23.0; extra == "efficient-llm"
Provides-Extra: all
Requires-Dist: pure-visual-grounder[local-dual-llm]; extra == "all"
Requires-Dist: pure-visual-grounder[efficient-llm]; extra == "all"
Dynamic: author
Dynamic: license-file
Dynamic: requires-python
